setup.py
funnykulka/__init__.py
funnykulka/text.py
funnykulka.egg-info/PKG-INFO
funnykulka.egg-info/SOURCES.txt
funnykulka.egg-info/dependency_links.txt
funnykulka.egg-info/not-zip-safe
funnykulka.egg-info/requires.txt
funnykulka.egg-info/top_level.txt