Metadata-Version: 1.0
Name: funnykulka
Version: 0.2
Summary: The funniest joke in the world
Home-page: http://github.com/GanadiniAkshay
Author: Akshay Kulkarni
Author-email: akshaykulkarni.2104@gmail.com
License: MIT
Platform: UNKNOWN
